grammdb/__init__.py
grammdb/contracts.py
grammdb/database.py
grammdb/exceptions.py
grammdb/operations.py
grammdb/py.typed
grammdb/transactions.py
grammdb/types.py
grammdb-0.1.0.dist-info/METADATA
grammdb-0.1.0.dist-info/WHEEL
grammdb-0.1.0.dist-info/licenses/LICENSE
grammdb-0.1.0.dist-info/RECORD
