Metadata-Version: 2.4
Name: grammdb
Version: 0.1.0
Summary: GrammAcc's Async Data Layer for Python Apps
Author: GrammAcc
Maintainer: GrammAcc
License-File: LICENSE
Requires-Python: >=3.12
Requires-Dist: sqlalchemy[asyncio]
Provides-Extra: dev
Requires-Dist: hatch; extra == 'dev'
